{"frames":{"tentabot01":{"frame":{"x":0,"y":548,"w":190,"h":176},"rotated":false,"trimmed":false,"spriteSourceSize":{"x":0,"y":0,"w":190,"h":176},"sourceSize":{"w":190,"h":176}},"tentabot02":{"frame":{"x":382,"y":354,"w":190,"h":176},"rotated":false,"trimmed":false,"spriteSourceSize":{"x":0,"y":0,"w":190,"h":176},"sourceSize":{"w":190,"h":176}},"tentabot03":{"frame":{"x":191,"y":371,"w":190,"h":176},"rotated":false,"trimmed":false,"spriteSourceSize":{"x":0,"y":0,"w":190,"h":176},"sourceSize":{"w":190,"h":176}},"tentabot04":{"frame":{"x":382,"y":548,"w":190,"h":176},"rotated":false,"trimmed":false,"spriteSourceSize":{"x":0,"y":0,"w":190,"h":176},"sourceSize":{"w":190,"h":176}},"tentabot05":{"frame":{"x":0,"y":194,"w":190,"h":176},"rotated":false,"trimmed":false,"spriteSourceSize":{"x":0,"y":0,"w":190,"h":176},"sourceSize":{"w":190,"h":176}},"fire01":{"frame":{"x":191,"y":177,"w":190,"h":176},"rotated":false,"trimmed":false,"spriteSourceSize":{"x":0,"y":0,"w":190,"h":176},"sourceSize":{"w":190,"h":176}},"fire02":{"frame":{"x":191,"y":0,"w":190,"h":176},"rotated":false,"trimmed":false,"spriteSourceSize":{"x":0,"y":0,"w":190,"h":176},"sourceSize":{"w":190,"h":176}},"fire03":{"frame":{"x":0,"y":0,"w":190,"h":176},"rotated":false,"trimmed":false,"spriteSourceSize":{"x":0,"y":0,"w":190,"h":176},"sourceSize":{"w":190,"h":176}},"takehit01":{"frame":{"x":191,"y":548,"w":190,"h":176},"rotated":false,"trimmed":false,"spriteSourceSize":{"x":0,"y":0,"w":190,"h":176},"sourceSize":{"w":190,"h":176}},"takehit02":{"frame":{"x":0,"y":371,"w":190,"h":176},"rotated":false,"trimmed":false,"spriteSourceSize":{"x":0,"y":0,"w":190,"h":176},"sourceSize":{"w":190,"h":176}},"takehit03":{"frame":{"x":382,"y":177,"w":190,"h":176},"rotated":false,"trimmed":false,"spriteSourceSize":{"x":0,"y":0,"w":190,"h":176},"sourceSize":{"w":190,"h":176}},"takehit04":{"frame":{"x":382,"y":0,"w":190,"h":176},"rotated":false,"trimmed":false,"spriteSourceSize":{"x":0,"y":0,"w":190,"h":176},"sourceSize":{"w":190,"h":176}},"withFire":{"frame":{"x":58,"y":177,"w":57,"h":16},"rotated":false,"trimmed":false,"spriteSourceSize":{"x":0,"y":0,"w":57,"h":16},"sourceSize":{"w":57,"h":16}},"withoutFire":{"frame":{"x":0,"y":177,"w":57,"h":16},"rotated":false,"trimmed":false,"spriteSourceSize":{"x":0,"y":0,"w":57,"h":16},"sourceSize":{"w":57,"h":16}}},"meta":{"app":"http://www.leshylabs.com/apps/sstool/","version":"Leshy SpriteSheet Tool v0.8.1","size":{"w":572,"h":724},"scale":1}}